Workbook

Sheet Resumo
B2: =HYPERLINK("#'Resumo'!B2","Resumo") -> Resumo | C2: =HYPERLINK("#'Titular'!B2","Titular") -> Titular | D2: =HYPERLINK("#'Bancos'!B2","Bancos") -> Bancos | E2: =HYPERLINK("#'Rendimentos'!B2","Rendimentos") -> Rendimentos | F2: =HYPERLINK("#'Bens'!B2","Bens") -> Bens | G2: =HYPERLINK("#'Pagamentos'!B2","Pagamentos") -> Pagamentos | H2: =HYPERLINK("#'Documentos'!B2","Documentos") -> Documentos
B4: Agregador de dados para Imposto de Renda
B7: Ano-calendário | C7: 2025
B9: Saldos bancários | E9: Rendimentos brutos | H9: Bens e direitos | K9: Pagamentos dedutíveis | N9: Documentos pendentes
B10: =SUM(Bancos!E7:E26) -> 23500 | E10: =SUM(Rendimentos!F7:F26) -> 13450 | H10: =SUM(Bens!F7:F26) -> 39200 | K10: =SUMIFS(Pagamentos!F7:F26,Pagamentos!G7:G26,"Sim") -> 2250 | N10: =COUNTIFS(Documentos!D7:D26,"Pendente") -> 2
B14: Verificação do preenchimento | H14: Links rápidos
B15: Etapa | E15: Situação
B16: Dados do titular | E16: =IF(Titular!D7="","Pendente","Concluído") -> Concluído | H16: =HYPERLINK("https://www.gov.br/receitafederal/pt-br/assuntos/meu-imposto-de-renda","Meu Imposto de Renda - Receita Federal") -> Meu Imposto de Renda - Receita Federal
B17: Contas bancárias | E17: =IF(COUNTA(Bancos!B7:B26)=0,"Pendente",IF(COUNTIFS(Bancos!H7:H26,"Revisar")>0,"Revisar","Concluído")) -> Concluído
B18: Rendimentos | E18: =IF(COUNTA(Rendimentos!B7:B26)=0,"Pendente",IF(COUNTIFS(Rendimentos!I7:I26,"Revisar")>0,"Revisar","Concluído")) -> Concluído | H18: =HYPERLINK("https://cav.receita.fazenda.gov.br/","Portal e-CAC") -> Portal e-CAC
B19: Documentos | E19: =IF(COUNTIFS(Documentos!G7:G26,"Revisar")>0,"Revisar",IF(N10=0,"Concluído","Pendente")) -> Pendente

Sheet Titular
B2: =HYPERLINK("#'Resumo'!B2","Resumo") -> Resumo | C2: =HYPERLINK("#'Titular'!B2","Titular") -> Titular | D2: =HYPERLINK("#'Bancos'!B2","Bancos") -> Bancos | E2: =HYPERLINK("#'Rendimentos'!B2","Rendimentos") -> Rendimentos | F2: =HYPERLINK("#'Bens'!B2","Bens") -> Bens | G2: =HYPERLINK("#'Pagamentos'!B2","Pagamentos") -> Pagamentos | H2: =HYPERLINK("#'Documentos'!B2","Documentos") -> Documentos
B4: Dados do titular
B7: Nome completo | D7: Pessoa Exemplo
B8: CPF | D8: 000.000.000-00
B9: Data de nascimento | D9: 34700
B10: Título de eleitor | D10: 000000000000
B11: Cônjuge
B12: Endereço | D12: Endereço fictício
B13: CEP | D13: 00000-000
B14: Telefone | D14: (00) 00000-0000
B15: E-mail | D15: exemplo@email.com
B16: Alteração cadastral desde a última declaração? | D16: Não
B17: Cônjuge como dependente? | D17: Não
B18: Residente no exterior? | D18: Não

Sheet Bancos
B2: =HYPERLINK("#'Resumo'!B2","Resumo") -> Resumo | C2: =HYPERLINK("#'Titular'!B2","Titular") -> Titular | D2: =HYPERLINK("#'Bancos'!B2","Bancos") -> Bancos | E2: =HYPERLINK("#'Rendimentos'!B2","Rendimentos") -> Rendimentos | F2: =HYPERLINK("#'Bens'!B2","Bens") -> Bens | G2: =HYPERLINK("#'Pagamentos'!B2","Pagamentos") -> Pagamentos | H2: =HYPERLINK("#'Documentos'!B2","Documentos") -> Documentos
B4: Contas e informes bancários
B6: Instituição financeira | C6: Tipo de conta | D6: Titular | E6: Saldo em 31/12 | F6: Informe recebido? | G6: Arquivo ou localização | H6: Validação
B7: 1 - Banco do Brasil | C7: Conta corrente | D7: Titular | E7: 12500 | F7: Sim | G7: informe_bb.pdf | H7: =IF(COUNTA(B7:G7)=0,"",IF(AND(COUNTIFS(Listas!$A$2:$A$51,B7)=1,COUNTIFS(Listas!$C$2:$C$7,C7)=1,D7<>"",ISNUMBER(E7),OR(F7="Sim",F7="Pendente",F7="Não aplicável")),"OK","Revisar")) -> OK
B8: 260 - Nubank | C8: Conta de pagamento | D8: Titular | E8: 4800 | F8: Sim | G8: informe_nubank.pdf | H8: =IF(COUNTA(B8:G8)=0,"",IF(AND(COUNTIFS(Listas!$A$2:$A$51,B8)=1,COUNTIFS(Listas!$C$2:$C$7,C8)=1,D8<>"",ISNUMBER(E8),OR(F8="Sim",F8="Pendente",F8="Não aplicável")),"OK","Revisar")) -> OK
B9: 77 - Banco Inter | C9: Conta corrente | D9: Titular | E9: 6200 | F9: Pendente | H9: =IF(COUNTA(B9:G9)=0,"",IF(AND(COUNTIFS(Listas!$A$2:$A$51,B9)=1,COUNTIFS(Listas!$C$2:$C$7,C9)=1,D9<>"",ISNUMBER(E9),OR(F9="Sim",F9="Pendente",F9="Não aplicável")),"OK","Revisar")) -> OK
H10: =IF(COUNTA(B10:G10)=0,"",IF(AND(COUNTIFS(Listas!$A$2:$A$51,B10)=1,COUNTIFS(Listas!$C$2:$C$7,C10)=1,D10<>"",ISNUMBER(E10),OR(F10="Sim",F10="Pendente",F10="Não aplicável")),"OK","Revisar"))
H11: =IF(COUNTA(B11:G11)=0,"",IF(AND(COUNTIFS(Listas!$A$2:$A$51,B11)=1,COUNTIFS(Listas!$C$2:$C$7,C11)=1,D11<>"",ISNUMBER(E11),OR(F11="Sim",F11="Pendente",F11="Não aplicável")),"OK","Revisar"))
H12: =IF(COUNTA(B12:G12)=0,"",IF(AND(COUNTIFS(Listas!$A$2:$A$51,B12)=1,COUNTIFS(Listas!$C$2:$C$7,C12)=1,D12<>"",ISNUMBER(E12),OR(F12="Sim",F12="Pendente",F12="Não aplicável")),"OK","Revisar"))
H13: =IF(COUNTA(B13:G13)=0,"",IF(AND(COUNTIFS(Listas!$A$2:$A$51,B13)=1,COUNTIFS(Listas!$C$2:$C$7,C13)=1,D13<>"",ISNUMBER(E13),OR(F13="Sim",F13="Pendente",F13="Não aplicável")),"OK","Revisar"))
H14: =IF(COUNTA(B14:G14)=0,"",IF(AND(COUNTIFS(Listas!$A$2:$A$51,B14)=1,COUNTIFS(Listas!$C$2:$C$7,C14)=1,D14<>"",ISNUMBER(E14),OR(F14="Sim",F14="Pendente",F14="Não aplicável")),"OK","Revisar"))
H15: =IF(COUNTA(B15:G15)=0,"",IF(AND(COUNTIFS(Listas!$A$2:$A$51,B15)=1,COUNTIFS(Listas!$C$2:$C$7,C15)=1,D15<>"",ISNUMBER(E15),OR(F15="Sim",F15="Pendente",F15="Não aplicável")),"OK","Revisar"))
H16: =IF(COUNTA(B16:G16)=0,"",IF(AND(COUNTIFS(Listas!$A$2:$A$51,B16)=1,COUNTIFS(Listas!$C$2:$C$7,C16)=1,D16<>"",ISNUMBER(E16),OR(F16="Sim",F16="Pendente",F16="Não aplicável")),"OK","Revisar"))
H17: =IF(COUNTA(B17:G17)=0,"",IF(AND(COUNTIFS(Listas!$A$2:$A$51,B17)=1,COUNTIFS(Listas!$C$2:$C$7,C17)=1,D17<>"",ISNUMBER(E17),OR(F17="Sim",F17="Pendente",F17="Não aplicável")),"OK","Revisar"))
H18: =IF(COUNTA(B18:G18)=0,"",IF(AND(COUNTIFS(Listas!$A$2:$A$51,B18)=1,COUNTIFS(Listas!$C$2:$C$7,C18)=1,D18<>"",ISNUMBER(E18),OR(F18="Sim",F18="Pendente",F18="Não aplicável")),"OK","Revisar"))
H19: =IF(COUNTA(B19:G19)=0,"",IF(AND(COUNTIFS(Listas!$A$2:$A$51,B19)=1,COUNTIFS(Listas!$C$2:$C$7,C19)=1,D19<>"",ISNUMBER(E19),OR(F19="Sim",F19="Pendente",F19="Não aplicável")),"OK","Revisar"))
H20: =IF(COUNTA(B20:G20)=0,"",IF(AND(COUNTIFS(Listas!$A$2:$A$51,B20)=1,COUNTIFS(Listas!$C$2:$C$7,C20)=1,D20<>"",ISNUMBER(E20),OR(F20="Sim",F20="Pendente",F20="Não aplicável")),"OK","Revisar"))
H21: =IF(COUNTA(B21:G21)=0,"",IF(AND(COUNTIFS(Listas!$A$2:$A$51,B21)=1,COUNTIFS(Listas!$C$2:$C$7,C21)=1,D21<>"",ISNUMBER(E21),OR(F21="Sim",F21="Pendente",F21="Não aplicável")),"OK","Revisar"))
... H26: =IF(COUNTA(B26:G26)=0,"",IF(AND(COUNTIFS(Listas!$A$2:$A$51,B26)=1,COUNTIFS(Listas!$C$2:$C$7,C26)=1,D26<>"",ISNUMBER(E26),OR(F26="Sim",F26="Pendente",F26="Não aplicável")),"OK","Revisar"))

Sheet Rendimentos
B2: =HYPERLINK("#'Resumo'!B2","Resumo") -> Resumo | C2: =HYPERLINK("#'Titular'!B2","Titular") -> Titular | D2: =HYPERLINK("#'Bancos'!B2","Bancos") -> Bancos | E2: =HYPERLINK("#'Rendimentos'!B2","Rendimentos") -> Rendimentos | F2: =HYPERLINK("#'Bens'!B2","Bens") -> Bens | G2: =HYPERLINK("#'Pagamentos'!B2","Pagamentos") -> Pagamentos | H2: =HYPERLINK("#'Documentos'!B2","Documentos") -> Documentos
B4: Rendimentos recebidos
B6: Data | C6: Categoria | D6: Fonte pagadora | E6: CPF ou CNPJ | F6: Rendimento bruto | G6: IR retido | H6: Comprovante | I6: Validação
B7: 45688 | C7: Salário | D7: Empresa Exemplo Ltda. | E7: 00.000.000/0000-00 | F7: 6500 | G7: 420 | H7: holerite_jan.pdf | I7: =IF(COUNTA(B7:H7)=0,"",IF(AND(ISNUMBER(B7),COUNTIFS(Listas!$E$2:$E$9,C7)=1,D7<>"",E7<>"",ISNUMBER(F7),ISNUMBER(G7)),"OK","Revisar")) -> OK
B8: 45716 | C8: Salário | D8: Empresa Exemplo Ltda. | E8: 00.000.000/0000-00 | F8: 6500 | G8: 420 | H8: holerite_fev.pdf | I8: =IF(COUNTA(B8:H8)=0,"",IF(AND(ISNUMBER(B8),COUNTIFS(Listas!$E$2:$E$9,C8)=1,D8<>"",E8<>"",ISNUMBER(F8),ISNUMBER(G8)),"OK","Revisar")) -> OK
B9: 45731 | C9: Dividendos | D9: Empresa Fictícia S.A. | E9: 00.000.000/0000-00 | F9: 450 | G9: 0 | H9: informe_dividendos.pdf | I9: =IF(COUNTA(B9:H9)=0,"",IF(AND(ISNUMBER(B9),COUNTIFS(Listas!$E$2:$E$9,C9)=1,D9<>"",E9<>"",ISNUMBER(F9),ISNUMBER(G9)),"OK","Revisar")) -> OK
I10: =IF(COUNTA(B10:H10)=0,"",IF(AND(ISNUMBER(B10),COUNTIFS(Listas!$E$2:$E$9,C10)=1,D10<>"",E10<>"",ISNUMBER(F10),ISNUMBER(G10)),"OK","Revisar"))
I11: =IF(COUNTA(B11:H11)=0,"",IF(AND(ISNUMBER(B11),COUNTIFS(Listas!$E$2:$E$9,C11)=1,D11<>"",E11<>"",ISNUMBER(F11),ISNUMBER(G11)),"OK","Revisar"))
I12: =IF(COUNTA(B12:H12)=0,"",IF(AND(ISNUMBER(B12),COUNTIFS(Listas!$E$2:$E$9,C12)=1,D12<>"",E12<>"",ISNUMBER(F12),ISNUMBER(G12)),"OK","Revisar"))
I13: =IF(COUNTA(B13:H13)=0,"",IF(AND(ISNUMBER(B13),COUNTIFS(Listas!$E$2:$E$9,C13)=1,D13<>"",E13<>"",ISNUMBER(F13),ISNUMBER(G13)),"OK","Revisar"))
I14: =IF(COUNTA(B14:H14)=0,"",IF(AND(ISNUMBER(B14),COUNTIFS(Listas!$E$2:$E$9,C14)=1,D14<>"",E14<>"",ISNUMBER(F14),ISNUMBER(G14)),"OK","Revisar"))
I15: =IF(COUNTA(B15:H15)=0,"",IF(AND(ISNUMBER(B15),COUNTIFS(Listas!$E$2:$E$9,C15)=1,D15<>"",E15<>"",ISNUMBER(F15),ISNUMBER(G15)),"OK","Revisar"))
I16: =IF(COUNTA(B16:H16)=0,"",IF(AND(ISNUMBER(B16),COUNTIFS(Listas!$E$2:$E$9,C16)=1,D16<>"",E16<>"",ISNUMBER(F16),ISNUMBER(G16)),"OK","Revisar"))
I17: =IF(COUNTA(B17:H17)=0,"",IF(AND(ISNUMBER(B17),COUNTIFS(Listas!$E$2:$E$9,C17)=1,D17<>"",E17<>"",ISNUMBER(F17),ISNUMBER(G17)),"OK","Revisar"))
I18: =IF(COUNTA(B18:H18)=0,"",IF(AND(ISNUMBER(B18),COUNTIFS(Listas!$E$2:$E$9,C18)=1,D18<>"",E18<>"",ISNUMBER(F18),ISNUMBER(G18)),"OK","Revisar"))
I19: =IF(COUNTA(B19:H19)=0,"",IF(AND(ISNUMBER(B19),COUNTIFS(Listas!$E$2:$E$9,C19)=1,D19<>"",E19<>"",ISNUMBER(F19),ISNUMBER(G19)),"OK","Revisar"))
I20: =IF(COUNTA(B20:H20)=0,"",IF(AND(ISNUMBER(B20),COUNTIFS(Listas!$E$2:$E$9,C20)=1,D20<>"",E20<>"",ISNUMBER(F20),ISNUMBER(G20)),"OK","Revisar"))
I21: =IF(COUNTA(B21:H21)=0,"",IF(AND(ISNUMBER(B21),COUNTIFS(Listas!$E$2:$E$9,C21)=1,D21<>"",E21<>"",ISNUMBER(F21),ISNUMBER(G21)),"OK","Revisar"))
... I26: =IF(COUNTA(B26:H26)=0,"",IF(AND(ISNUMBER(B26),COUNTIFS(Listas!$E$2:$E$9,C26)=1,D26<>"",E26<>"",ISNUMBER(F26),ISNUMBER(G26)),"OK","Revisar"))

Sheet Bens
B2: =HYPERLINK("#'Resumo'!B2","Resumo") -> Resumo | C2: =HYPERLINK("#'Titular'!B2","Titular") -> Titular | D2: =HYPERLINK("#'Bancos'!B2","Bancos") -> Bancos | E2: =HYPERLINK("#'Rendimentos'!B2","Rendimentos") -> Rendimentos | F2: =HYPERLINK("#'Bens'!B2","Bens") -> Bens | G2: =HYPERLINK("#'Pagamentos'!B2","Pagamentos") -> Pagamentos | H2: =HYPERLINK("#'Documentos'!B2","Documentos") -> Documentos
B4: Bens e direitos
B6: Tipo | C6: Descrição | D6: Data de aquisição | E6: Valor anterior | F6: Valor atual | G6: Declarar? | H6: Documento | I6: Validação
B7: Veículo | C7: Veículo fictício | D7: 45087 | E7: 35000 | F7: 35000 | G7: Sim | H7: documento_veiculo.pdf | I7: =IF(COUNTA(B7:H7)=0,"",IF(AND(COUNTIFS(Listas!$G$2:$G$9,B7)=1,C7<>"",ISNUMBER(D7),ISNUMBER(E7),ISNUMBER(F7),OR(G7="Sim",G7="Não",G7="Verificar")),"OK","Revisar")) -> OK
B8: Investimento | C8: Cotas de fundo fictício | D8: 45717 | E8: 0 | F8: 4200 | G8: Sim | H8: informe_investimento.pdf | I8: =IF(COUNTA(B8:H8)=0,"",IF(AND(COUNTIFS(Listas!$G$2:$G$9,B8)=1,C8<>"",ISNUMBER(D8),ISNUMBER(E8),ISNUMBER(F8),OR(G8="Sim",G8="Não",G8="Verificar")),"OK","Revisar")) -> OK
I9: =IF(COUNTA(B9:H9)=0,"",IF(AND(COUNTIFS(Listas!$G$2:$G$9,B9)=1,C9<>"",ISNUMBER(D9),ISNUMBER(E9),ISNUMBER(F9),OR(G9="Sim",G9="Não",G9="Verificar")),"OK","Revisar"))
I10: =IF(COUNTA(B10:H10)=0,"",IF(AND(COUNTIFS(Listas!$G$2:$G$9,B10)=1,C10<>"",ISNUMBER(D10),ISNUMBER(E10),ISNUMBER(F10),OR(G10="Sim",G10="Não",G10="Verificar")),"OK","Revisar"))
I11: =IF(COUNTA(B11:H11)=0,"",IF(AND(COUNTIFS(Listas!$G$2:$G$9,B11)=1,C11<>"",ISNUMBER(D11),ISNUMBER(E11),ISNUMBER(F11),OR(G11="Sim",G11="Não",G11="Verificar")),"OK","Revisar"))
I12: =IF(COUNTA(B12:H12)=0,"",IF(AND(COUNTIFS(Listas!$G$2:$G$9,B12)=1,C12<>"",ISNUMBER(D12),ISNUMBER(E12),ISNUMBER(F12),OR(G12="Sim",G12="Não",G12="Verificar")),"OK","Revisar"))
I13: =IF(COUNTA(B13:H13)=0,"",IF(AND(COUNTIFS(Listas!$G$2:$G$9,B13)=1,C13<>"",ISNUMBER(D13),ISNUMBER(E13),ISNUMBER(F13),OR(G13="Sim",G13="Não",G13="Verificar")),"OK","Revisar"))
I14: =IF(COUNTA(B14:H14)=0,"",IF(AND(COUNTIFS(Listas!$G$2:$G$9,B14)=1,C14<>"",ISNUMBER(D14),ISNUMBER(E14),ISNUMBER(F14),OR(G14="Sim",G14="Não",G14="Verificar")),"OK","Revisar"))
I15: =IF(COUNTA(B15:H15)=0,"",IF(AND(COUNTIFS(Listas!$G$2:$G$9,B15)=1,C15<>"",ISNUMBER(D15),ISNUMBER(E15),ISNUMBER(F15),OR(G15="Sim",G15="Não",G15="Verificar")),"OK","Revisar"))
I16: =IF(COUNTA(B16:H16)=0,"",IF(AND(COUNTIFS(Listas!$G$2:$G$9,B16)=1,C16<>"",ISNUMBER(D16),ISNUMBER(E16),ISNUMBER(F16),OR(G16="Sim",G16="Não",G16="Verificar")),"OK","Revisar"))
I17: =IF(COUNTA(B17:H17)=0,"",IF(AND(COUNTIFS(Listas!$G$2:$G$9,B17)=1,C17<>"",ISNUMBER(D17),ISNUMBER(E17),ISNUMBER(F17),OR(G17="Sim",G17="Não",G17="Verificar")),"OK","Revisar"))
I18: =IF(COUNTA(B18:H18)=0,"",IF(AND(COUNTIFS(Listas!$G$2:$G$9,B18)=1,C18<>"",ISNUMBER(D18),ISNUMBER(E18),ISNUMBER(F18),OR(G18="Sim",G18="Não",G18="Verificar")),"OK","Revisar"))
I19: =IF(COUNTA(B19:H19)=0,"",IF(AND(COUNTIFS(Listas!$G$2:$G$9,B19)=1,C19<>"",ISNUMBER(D19),ISNUMBER(E19),ISNUMBER(F19),OR(G19="Sim",G19="Não",G19="Verificar")),"OK","Revisar"))
I20: =IF(COUNTA(B20:H20)=0,"",IF(AND(COUNTIFS(Listas!$G$2:$G$9,B20)=1,C20<>"",ISNUMBER(D20),ISNUMBER(E20),ISNUMBER(F20),OR(G20="Sim",G20="Não",G20="Verificar")),"OK","Revisar"))
... I26: =IF(COUNTA(B26:H26)=0,"",IF(AND(COUNTIFS(Listas!$G$2:$G$9,B26)=1,C26<>"",ISNUMBER(D26),ISNUMBER(E26),ISNUMBER(F26),OR(G26="Sim",G26="Não",G26="Verificar")),"OK","Revisar"))

Sheet Pagamentos
B2: =HYPERLINK("#'Resumo'!B2","Resumo") -> Resumo | C2: =HYPERLINK("#'Titular'!B2","Titular") -> Titular | D2: =HYPERLINK("#'Bancos'!B2","Bancos") -> Bancos | E2: =HYPERLINK("#'Rendimentos'!B2","Rendimentos") -> Rendimentos | F2: =HYPERLINK("#'Bens'!B2","Bens") -> Bens | G2: =HYPERLINK("#'Pagamentos'!B2","Pagamentos") -> Pagamentos | H2: =HYPERLINK("#'Documentos'!B2","Documentos") -> Documentos
B4: Pagamentos e possíveis deduções
B6: Data | C6: Categoria | D6: Beneficiário | E6: CPF ou CNPJ | F6: Valor pago | G6: Dedutível? | H6: Comprovante | I6: Validação
B7: 45698 | C7: Saúde | D7: Clínica Exemplo | E7: 00.000.000/0000-00 | F7: 1800 | G7: Sim | H7: recibo_clinica.pdf | I7: =IF(COUNTA(B7:H7)=0,"",IF(AND(ISNUMBER(B7),COUNTIFS(Listas!$I$2:$I$9,C7)=1,D7<>"",E7<>"",ISNUMBER(F7),OR(G7="Sim",G7="Não")),"OK","Revisar")) -> OK
B8: 45721 | C8: Educação | D8: Instituição Exemplo | E8: 00.000.000/0000-00 | F8: 450 | G8: Sim | H8: mensalidade_mar.pdf | I8: =IF(COUNTA(B8:H8)=0,"",IF(AND(ISNUMBER(B8),COUNTIFS(Listas!$I$2:$I$9,C8)=1,D8<>"",E8<>"",ISNUMBER(F8),OR(G8="Sim",G8="Não")),"OK","Revisar")) -> OK
B9: 45759 | C9: Doação | D9: Projeto Fictício | E9: 00.000.000/0000-00 | F9: 200 | G9: Verificar | H9: recibo_doacao.pdf | I9: =IF(COUNTA(B9:H9)=0,"",IF(AND(ISNUMBER(B9),COUNTIFS(Listas!$I$2:$I$9,C9)=1,D9<>"",E9<>"",ISNUMBER(F9),OR(G9="Sim",G9="Não")),"OK","Revisar")) -> Revisar
I10: =IF(COUNTA(B10:H10)=0,"",IF(AND(ISNUMBER(B10),COUNTIFS(Listas!$I$2:$I$9,C10)=1,D10<>"",E10<>"",ISNUMBER(F10),OR(G10="Sim",G10="Não")),"OK","Revisar"))
I11: =IF(COUNTA(B11:H11)=0,"",IF(AND(ISNUMBER(B11),COUNTIFS(Listas!$I$2:$I$9,C11)=1,D11<>"",E11<>"",ISNUMBER(F11),OR(G11="Sim",G11="Não")),"OK","Revisar"))
I12: =IF(COUNTA(B12:H12)=0,"",IF(AND(ISNUMBER(B12),COUNTIFS(Listas!$I$2:$I$9,C12)=1,D12<>"",E12<>"",ISNUMBER(F12),OR(G12="Sim",G12="Não")),"OK","Revisar"))
I13: =IF(COUNTA(B13:H13)=0,"",IF(AND(ISNUMBER(B13),COUNTIFS(Listas!$I$2:$I$9,C13)=1,D13<>"",E13<>"",ISNUMBER(F13),OR(G13="Sim",G13="Não")),"OK","Revisar"))
I14: =IF(COUNTA(B14:H14)=0,"",IF(AND(ISNUMBER(B14),COUNTIFS(Listas!$I$2:$I$9,C14)=1,D14<>"",E14<>"",ISNUMBER(F14),OR(G14="Sim",G14="Não")),"OK","Revisar"))
I15: =IF(COUNTA(B15:H15)=0,"",IF(AND(ISNUMBER(B15),COUNTIFS(Listas!$I$2:$I$9,C15)=1,D15<>"",E15<>"",ISNUMBER(F15),OR(G15="Sim",G15="Não")),"OK","Revisar"))
I16: =IF(COUNTA(B16:H16)=0,"",IF(AND(ISNUMBER(B16),COUNTIFS(Listas!$I$2:$I$9,C16)=1,D16<>"",E16<>"",ISNUMBER(F16),OR(G16="Sim",G16="Não")),"OK","Revisar"))
I17: =IF(COUNTA(B17:H17)=0,"",IF(AND(ISNUMBER(B17),COUNTIFS(Listas!$I$2:$I$9,C17)=1,D17<>"",E17<>"",ISNUMBER(F17),OR(G17="Sim",G17="Não")),"OK","Revisar"))
I18: =IF(COUNTA(B18:H18)=0,"",IF(AND(ISNUMBER(B18),COUNTIFS(Listas!$I$2:$I$9,C18)=1,D18<>"",E18<>"",ISNUMBER(F18),OR(G18="Sim",G18="Não")),"OK","Revisar"))
I19: =IF(COUNTA(B19:H19)=0,"",IF(AND(ISNUMBER(B19),COUNTIFS(Listas!$I$2:$I$9,C19)=1,D19<>"",E19<>"",ISNUMBER(F19),OR(G19="Sim",G19="Não")),"OK","Revisar"))
I20: =IF(COUNTA(B20:H20)=0,"",IF(AND(ISNUMBER(B20),COUNTIFS(Listas!$I$2:$I$9,C20)=1,D20<>"",E20<>"",ISNUMBER(F20),OR(G20="Sim",G20="Não")),"OK","Revisar"))
I21: =IF(COUNTA(B21:H21)=0,"",IF(AND(ISNUMBER(B21),COUNTIFS(Listas!$I$2:$I$9,C21)=1,D21<>"",E21<>"",ISNUMBER(F21),OR(G21="Sim",G21="Não")),"OK","Revisar"))
... I26: =IF(COUNTA(B26:H26)=0,"",IF(AND(ISNUMBER(B26),COUNTIFS(Listas!$I$2:$I$9,C26)=1,D26<>"",E26<>"",ISNUMBER(F26),OR(G26="Sim",G26="Não")),"OK","Revisar"))

Sheet Documentos
B2: =HYPERLINK("#'Resumo'!B2","Resumo") -> Resumo | C2: =HYPERLINK("#'Titular'!B2","Titular") -> Titular | D2: =HYPERLINK("#'Bancos'!B2","Bancos") -> Bancos | E2: =HYPERLINK("#'Rendimentos'!B2","Rendimentos") -> Rendimentos | F2: =HYPERLINK("#'Bens'!B2","Bens") -> Bens | G2: =HYPERLINK("#'Pagamentos'!B2","Pagamentos") -> Pagamentos | H2: =HYPERLINK("#'Documentos'!B2","Documentos") -> Documentos
B4: Controle de documentos
B6: Categoria | C6: Documento | D6: Situação | E6: Arquivo ou localização | F6: Observação | G6: Validação
B7: Titular | C7: Documento de identificação | D7: Recebido | E7: documentos/identificacao.pdf | F7: Exemplo fictício | G7: =IF(COUNTA(B7:F7)=0,"",IF(AND(B7<>"",C7<>"",OR(D7="Pendente",D7="Recebido",D7="Não aplicável")),"OK","Revisar")) -> OK
B8: Bancos | C8: Informe Banco do Brasil | D8: Recebido | E8: informes/informe_bb.pdf | G8: =IF(COUNTA(B8:F8)=0,"",IF(AND(B8<>"",C8<>"",OR(D8="Pendente",D8="Recebido",D8="Não aplicável")),"OK","Revisar")) -> OK
B9: Bancos | C9: Informe Banco Inter | D9: Pendente | F9: Solicitar ao banco | G9: =IF(COUNTA(B9:F9)=0,"",IF(AND(B9<>"",C9<>"",OR(D9="Pendente",D9="Recebido",D9="Não aplicável")),"OK","Revisar")) -> OK
B10: Rendimentos | C10: Informe da fonte pagadora | D10: Recebido | E10: rendimentos/informe_empresa.pdf | G10: =IF(COUNTA(B10:F10)=0,"",IF(AND(B10<>"",C10<>"",OR(D10="Pendente",D10="Recebido",D10="Não aplicável")),"OK","Revisar")) -> OK
B11: Pagamentos | C11: Recibo de saúde | D11: Pendente | F11: Conferir CPF ou CNPJ | G11: =IF(COUNTA(B11:F11)=0,"",IF(AND(B11<>"",C11<>"",OR(D11="Pendente",D11="Recebido",D11="Não aplicável")),"OK","Revisar")) -> OK
G12: =IF(COUNTA(B12:F12)=0,"",IF(AND(B12<>"",C12<>"",OR(D12="Pendente",D12="Recebido",D12="Não aplicável")),"OK","Revisar"))
G13: =IF(COUNTA(B13:F13)=0,"",IF(AND(B13<>"",C13<>"",OR(D13="Pendente",D13="Recebido",D13="Não aplicável")),"OK","Revisar"))
G14: =IF(COUNTA(B14:F14)=0,"",IF(AND(B14<>"",C14<>"",OR(D14="Pendente",D14="Recebido",D14="Não aplicável")),"OK","Revisar"))
G15: =IF(COUNTA(B15:F15)=0,"",IF(AND(B15<>"",C15<>"",OR(D15="Pendente",D15="Recebido",D15="Não aplicável")),"OK","Revisar"))
G16: =IF(COUNTA(B16:F16)=0,"",IF(AND(B16<>"",C16<>"",OR(D16="Pendente",D16="Recebido",D16="Não aplicável")),"OK","Revisar"))
G17: =IF(COUNTA(B17:F17)=0,"",IF(AND(B17<>"",C17<>"",OR(D17="Pendente",D17="Recebido",D17="Não aplicável")),"OK","Revisar"))
G18: =IF(COUNTA(B18:F18)=0,"",IF(AND(B18<>"",C18<>"",OR(D18="Pendente",D18="Recebido",D18="Não aplicável")),"OK","Revisar"))
G19: =IF(COUNTA(B19:F19)=0,"",IF(AND(B19<>"",C19<>"",OR(D19="Pendente",D19="Recebido",D19="Não aplicável")),"OK","Revisar"))
G20: =IF(COUNTA(B20:F20)=0,"",IF(AND(B20<>"",C20<>"",OR(D20="Pendente",D20="Recebido",D20="Não aplicável")),"OK","Revisar"))
G21: =IF(COUNTA(B21:F21)=0,"",IF(AND(B21<>"",C21<>"",OR(D21="Pendente",D21="Recebido",D21="Não aplicável")),"OK","Revisar"))
G22: =IF(COUNTA(B22:F22)=0,"",IF(AND(B22<>"",C22<>"",OR(D22="Pendente",D22="Recebido",D22="Não aplicável")),"OK","Revisar"))
G23: =IF(COUNTA(B23:F23)=0,"",IF(AND(B23<>"",C23<>"",OR(D23="Pendente",D23="Recebido",D23="Não aplicável")),"OK","Revisar"))
... G26: =IF(COUNTA(B26:F26)=0,"",IF(AND(B26<>"",C26<>"",OR(D26="Pendente",D26="Recebido",D26="Não aplicável")),"OK","Revisar"))

Sheet Listas
A1: Bancos | C1: Tipos de conta | E1: Rendimentos | G1: Bens | I1: Pagamentos | K1: Fonte | L1: Descrição
A2: 1 - Banco do Brasil | B2: Apoio às listas suspensas e às validações do arquivo | C2: Conta corrente | E2: Salário | G2: Imóvel | I2: Saúde | K2: bancos_apoio.xlsx | L2: Lista de bancos disponibilizada no desafio DIO
A3: 102 - XP Investimentos CCTVM S.A. | C3: Conta poupança | E3: Pró-labore | G3: Veículo | I3: Educação | K3: projeto_completo.xlsx | L3: Modelo resolvido disponibilizado no desafio DIO
A4: 104 - Caixa Econômica Federal | B4: Listas de apoio e fontes | C4: Conta de pagamento | E4: Aposentadoria | G4: Investimento | I4: Previdência | K4: Uso | L4: Dados fictícios para demonstração; substitua apenas em cópia local
A5: 119 - Banco Western Union do Brasil | C5: Conta investimento | E5: Aluguel | G5: Conta bancária | I5: Pensão alimentícia | K5: Privacidade | L5: Não publique informações reais no GitHub
A6: 184 - Banco Itaú BBA S.A. | C6: Corretora | E6: Autônomo | G6: Participação societária | I6: Doação
A7: 197 - Stone Pagamentos | C7: Outro | E7: Dividendos | G7: Criptoativo | I7: Aluguel
A8: 208 - Banco BTG Pactual | E8: Rendimentos bancários | G8: Crédito a receber | I8: Serviços profissionais
A9: 212 - Banco Original | E9: Outros | G9: Outro | I9: Outros
A10: 218 - Banco Bonsucesso
A11: 229 - Banco Cruzeiro do Sul
A12: 237 - Banco Bradesco
A13: 24 - Banco de Pernambuco
A14: 241 - Banco Clássico
A15: 250 - Banco de Crédito e Varejo (BCV)
A16: 260 - Nubank
A17: 29 - Banco do Estado do Rio de Janeiro
A18: 290 - PagBank
A19: 3 - Banco da Amazônia
A20: 33 - Banco Santander
A21: 336 - C6 Bank
... A51: 82 - Banco Topázio
